LICENSE
setup.py
disco/__init__.py
disco/distributions/__init__.py
disco/distributions/base_distribution.py
disco/distributions/context_distribution.py
disco/distributions/dataset_context_distribution.py
disco/distributions/distribution.py
disco/distributions/lm_distribution.py
disco/distributions/single_context_distribution.py
disco/metrics/__init__.py
disco/metrics/base.py
disco/metrics/js.py
disco/metrics/kl.py
disco/metrics/tv.py
disco/samplers/__init__.py
disco/samplers/accumulation_sampler.py
disco/samplers/quasi_rejection_sampler.py
disco/samplers/sampler.py
disco/scorers/__init__.py
disco/scorers/boolean_scorer.py
disco/scorers/exponential_scorer.py
disco/scorers/pipeline_scorer.py
disco/scorers/positive_scorer.py
disco/scorers/scorer.py
disco/tuners/__init__.py
disco/tuners/cdpg_tuner.py
disco/tuners/dpg_tuner.py
disco/tuners/fcdpg_tuner.py
disco/tuners/fdpg_tuner.py
disco/tuners/tuner.py
disco/tuners/loggers/__init__.py
disco/tuners/loggers/base.py
disco/tuners/loggers/console.py
disco/tuners/loggers/json.py
disco/tuners/loggers/neptune.py
disco/tuners/loggers/wandb.py
disco/tuners/losses/__init__.py
disco/tuners/losses/base.py
disco/tuners/losses/js.py
disco/tuners/losses/kl.py
disco/tuners/losses/reverse_kl.py
disco/tuners/losses/tv.py
disco/utils/__init__.py
disco/utils/device.py
disco/utils/helpers.py
disco/utils/moving_average.py
disco/utils/observable.py
disco_generation.egg-info/PKG-INFO
disco_generation.egg-info/SOURCES.txt
disco_generation.egg-info/dependency_links.txt
disco_generation.egg-info/requires.txt
disco_generation.egg-info/top_level.txt