Metadata-Version: 2.1
Name: disco-generation
Version: 1.1.0
Summary: A toolkit for distributional control of generative models
Home-page: https://github.com/naver/disco
Author: Naver Labs Europe
Author-email: jos.rozen@naverlabs.com
License: Creative Commons Attribution-NonCommercial-ShareAlike 4.0
Platform: UNKNOWN
Classifier: Development Status :: 5 - Production/Stable
Classifier: Intended Audience :: Science/Research
Classifier: License :: Free for non-commercial use
Classifier: Operating System :: POSIX :: Linux
Classifier: Operating System :: MacOS
Classifier: Operating System :: Microsoft :: Windows
Classifier: Programming Language :: Python :: 3
Classifier: Programming Language :: Python :: 3.8
Classifier: Programming Language :: Python :: 3.9
Classifier: Programming Language :: Python :: 3.10
Requires-Python: >=3.8, <3.11
